elphem/__init__.py
elphem/common/__init__.py
elphem/common/atomic_weight.py
elphem/common/brillouin.py
elphem/common/distribution.py
elphem/common/function.py
elphem/common/stdout.py
elphem/common/unit.py
elphem/electron/__init__.py
elphem/electron/electron.py
elphem/elph/__init__.py
elphem/elph/electron_phonon.py
elphem/elph/green_function.py
elphem/lattice/__init__.py
elphem/lattice/cell.py
elphem/lattice/lattice.py
elphem/lattice/lattice_constant.py
elphem/lattice/path.py
elphem/lattice/primitive_cell.py
elphem/lattice/reciprocal_cell.py
elphem/lattice/rotation.py
elphem/phonon/__init__.py
elphem/phonon/phonon.py
tests/__init__.py
tests/common/__init__.py
tests/common/test_atomic_weight.py
tests/common/test_brillouin.py
tests/common/test_unit.py
tests/electron/__init__.py
tests/electron/test_electron.py
tests/elph/__init__.py
tests/elph/test_self_energy.py
tests/lattice/__init__.py
tests/lattice/test_lattice.py
tests/phonon/__init__.py
tests/phonon/test_phonon.py
elphem-0.3.3.dist-info/LICENSE
elphem-0.3.3.dist-info/METADATA
elphem-0.3.3.dist-info/WHEEL
elphem-0.3.3.dist-info/top_level.txt
elphem-0.3.3.dist-info/RECORD
