Metadata-Version: 2.1
Name: elphem
Version: 0.3.3
Summary: Elphem: Calculating electron-phonon interactions with the empty lattice.
Home-page: https://github.com/cohsh/elphem
Download-URL: https://github.com/cohsh/elphem
Author: Kohei Ishii
Author-email: 
Maintainer: Kohei Ishii
Maintainer-email: 
License: MIT
Classifier: License :: OSI Approved :: MIT License
Classifier: Programming Language :: Python
Classifier: Programming Language :: Python :: 3.10
Classifier: Programming Language :: Python :: 3.11
Classifier: Programming Language :: Python :: 3.12
License-File: LICENSE
Requires-Dist: numpy
Requires-Dist: scipy
